update_client.py
live_update_client-0.1.1.dist-info/METADATA
live_update_client-0.1.1.dist-info/WHEEL
live_update_client-0.1.1.dist-info/top_level.txt
live_update_client-0.1.1.dist-info/RECORD
